pqr/__init__.py
pqr/allocation.py
pqr/evaluation.py
pqr/picking.py
pqr/utils.py
pqr-1.0.1.dist-info/LICENSE
pqr-1.0.1.dist-info/WHEEL
pqr-1.0.1.dist-info/METADATA
pqr-1.0.1.dist-info/RECORD
